<?xml version="1.0" encoding="UTF-8"?>
<java-wsdl-mapping xmlns="http://java.sun.com/xml/ns/j2ee"
  xmlns:xsi="http://www.w3.org/2001/XMLSchema-instance"
  xsi:schemaLocation="http://java.sun.com/xml/ns/j2ee
  http://www.ibm.com/webservices/xsd/j2ee_jaxrpc_mapping_1_1.xsd"
  version="1.1">

    <package-mapping>
        <package-type>com.gssamerica.mdm.services.addremotekey</package-type>
        <namespaceURI>http://www.gssamerica.com/mdm/services/AddRemoteKeyService/</namespaceURI>
    </package-mapping>
    <package-mapping>
        <package-type>com.gssamerica.mdm.services</package-type>
        <namespaceURI>http://www.gssamerica.com/mdm/services</namespaceURI>
    </package-mapping>
    <java-xml-type-mapping>
        <java-type>com.gssamerica.mdm.services.ObjectNameType</java-type>
        <root-type-qname xmlns:typeNS="http://www.gssamerica.com/mdm/services">typeNS:objectNameType</root-type-qname>
        <qname-scope>complexType</qname-scope>
        <variable-mapping>
            <java-variable-name>language</java-variable-name>
            <xml-element-name>language</xml-element-name>
        </variable-mapping>
        <variable-mapping>
            <java-variable-name>name</java-variable-name>
            <xml-element-name>name</xml-element-name>
        </variable-mapping>
    </java-xml-type-mapping>
    <java-xml-type-mapping>
        <java-type>com.gssamerica.mdm.services.AddRemoteKeyRequestType</java-type>
        <root-type-qname xmlns:typeNS="http://www.gssamerica.com/mdm/services">typeNS:addRemoteKeyRequestType</root-type-qname>
        <qname-scope>complexType</qname-scope>
        <variable-mapping>
            <java-variable-name>recordIdentifier</java-variable-name>
            <xml-element-name>recordIdentifier</xml-element-name>
        </variable-mapping>
        <variable-mapping>
            <java-variable-name>repositoryInfo</java-variable-name>
            <xml-element-name>repositoryInfo</xml-element-name>
        </variable-mapping>
        <variable-mapping>
            <java-variable-name>configData</java-variable-name>
            <xml-element-name>configData</xml-element-name>
        </variable-mapping>
    </java-xml-type-mapping>
    <java-xml-type-mapping>
        <java-type>com.gssamerica.mdm.services.DataElementType</java-type>
        <root-type-qname xmlns:typeNS="http://www.gssamerica.com/mdm/services">typeNS:dataElementType</root-type-qname>
        <qname-scope>complexType</qname-scope>
        <variable-mapping>
            <java-variable-name>displayValue</java-variable-name>
            <xml-element-name>displayValue</xml-element-name>
        </variable-mapping>
        <variable-mapping>
            <java-variable-name>field</java-variable-name>
            <xml-element-name>field</xml-element-name>
        </variable-mapping>
        <variable-mapping>
            <java-variable-name>simpleValue</java-variable-name>
            <xml-element-name>simpleValue</xml-element-name>
        </variable-mapping>
        <variable-mapping>
            <java-variable-name>lookupValue</java-variable-name>
            <xml-element-name>lookupValue</xml-element-name>
        </variable-mapping>
    </java-xml-type-mapping>
    <java-xml-type-mapping>
        <java-type>com.gssamerica.mdm.services.ResultDefinitionType</java-type>
        <root-type-qname xmlns:typeNS="http://www.gssamerica.com/mdm/services">typeNS:resultDefinitionType</root-type-qname>
        <qname-scope>complexType</qname-scope>
        <variable-mapping>
            <java-variable-name>tableCode</java-variable-name>
            <xml-element-name>tableCode</xml-element-name>
        </variable-mapping>
        <variable-mapping>
            <java-variable-name>fieldListType</java-variable-name>
            <xml-element-name>fieldListType</xml-element-name>
        </variable-mapping>
        <variable-mapping>
            <java-variable-name>fieldDefinition</java-variable-name>
            <xml-element-name>fieldDefinition</xml-element-name>
        </variable-mapping>
        <variable-mapping>
            <java-variable-name>languageFilter</java-variable-name>
            <xml-element-name>languageFilter</xml-element-name>
        </variable-mapping>
        <variable-mapping>
            <java-variable-name>retrieveRemoteKeys</java-variable-name>
            <xml-element-name>retrieveRemoteKeys</xml-element-name>
        </variable-mapping>
        <variable-mapping>
            <java-variable-name>sortDefinition</java-variable-name>
            <xml-element-name>sortDefinition</xml-element-name>
        </variable-mapping>
        <variable-mapping>
            <java-variable-name>pageSize</java-variable-name>
            <xml-element-name>pageSize</xml-element-name>
        </variable-mapping>
        <variable-mapping>
            <java-variable-name>pageNumber</java-variable-name>
            <xml-element-name>pageNumber</xml-element-name>
        </variable-mapping>
    </java-xml-type-mapping>
    <java-xml-type-mapping>
        <java-type>com.gssamerica.mdm.services.DelRemoteKeyRequestType</java-type>
        <root-type-qname xmlns:typeNS="http://www.gssamerica.com/mdm/services">typeNS:delRemoteKeyRequestType</root-type-qname>
        <qname-scope>complexType</qname-scope>
        <variable-mapping>
            <java-variable-name>recordIdentifier</java-variable-name>
            <xml-element-name>recordIdentifier</xml-element-name>
        </variable-mapping>
        <variable-mapping>
            <java-variable-name>repositoryInfo</java-variable-name>
            <xml-element-name>repositoryInfo</xml-element-name>
        </variable-mapping>
        <variable-mapping>
            <java-variable-name>configData</java-variable-name>
            <xml-element-name>configData</xml-element-name>
        </variable-mapping>
    </java-xml-type-mapping>
    <java-xml-type-mapping>
        <java-type>com.gssamerica.mdm.services.RemoteSystemFilterType</java-type>
        <root-type-qname xmlns:typeNS="http://www.gssamerica.com/mdm/services">typeNS:remoteSystemFilterType</root-type-qname>
        <qname-scope>complexType</qname-scope>
        <variable-mapping>
            <java-variable-name>remoteSystemDefaultsOnly</java-variable-name>
            <xml-element-name>remoteSystemDefaultsOnly</xml-element-name>
        </variable-mapping>
        <variable-mapping>
            <java-variable-name>remoteSystem</java-variable-name>
            <xml-element-name>remoteSystem</xml-element-name>
        </variable-mapping>
    </java-xml-type-mapping>
    <java-xml-type-mapping>
        <java-type>com.gssamerica.mdm.services.SimpleValueType</java-type>
        <root-type-qname xmlns:typeNS="http://www.gssamerica.com/mdm/services">typeNS:simpleValueType</root-type-qname>
        <qname-scope>complexType</qname-scope>
        <variable-mapping>
            <java-variable-name>position</java-variable-name>
            <xml-element-name>position</xml-element-name>
        </variable-mapping>
        <variable-mapping>
            <java-variable-name>unifiedValue</java-variable-name>
            <xml-element-name>unifiedValue</xml-element-name>
        </variable-mapping>
        <variable-mapping>
            <java-variable-name>remoteKey</java-variable-name>
            <xml-element-name>remoteKey</xml-element-name>
        </variable-mapping>
    </java-xml-type-mapping>
    <java-xml-type-mapping>
        <java-type>com.gssamerica.mdm.services.RecordIdentifierRequestType</java-type>
        <root-type-qname xmlns:typeNS="http://www.gssamerica.com/mdm/services">typeNS:recordIdentifierRequestType</root-type-qname>
        <qname-scope>complexType</qname-scope>
        <variable-mapping>
            <java-variable-name>tableCode</java-variable-name>
            <xml-element-name>TableCode</xml-element-name>
        </variable-mapping>
        <variable-mapping>
            <java-variable-name>recordIdentifier</java-variable-name>
            <xml-element-name>recordIdentifier</xml-element-name>
        </variable-mapping>
        <variable-mapping>
            <java-variable-name>remoteSystemFilter</java-variable-name>
            <xml-element-name>remoteSystemFilter</xml-element-name>
        </variable-mapping>
    </java-xml-type-mapping>
    <java-xml-type-mapping>
        <java-type>com.gssamerica.mdm.services.RecordCriteriaType</java-type>
        <root-type-qname xmlns:typeNS="http://www.gssamerica.com/mdm/services">typeNS:recordCriteriaType</root-type-qname>
        <qname-scope>complexType</qname-scope>
        <variable-mapping>
            <java-variable-name>logicOperator</java-variable-name>
            <xml-element-name>logicOperator</xml-element-name>
        </variable-mapping>
        <variable-mapping>
            <java-variable-name>dataElementCriteria</java-variable-name>
            <xml-element-name>dataElementCriteria</xml-element-name>
        </variable-mapping>
        <variable-mapping>
            <java-variable-name>recordIdentifierCriteria</java-variable-name>
            <xml-element-name>recordIdentifierCriteria</xml-element-name>
        </variable-mapping>
        <variable-mapping>
            <java-variable-name>keywordCriteria</java-variable-name>
            <xml-element-name>keywordCriteria</xml-element-name>
        </variable-mapping>
        <variable-mapping>
            <java-variable-name>tableCode</java-variable-name>
            <xml-element-name>tableCode</xml-element-name>
        </variable-mapping>
    </java-xml-type-mapping>
    <java-xml-type-mapping>
        <java-type>com.gssamerica.mdm.services.SortDefinitionType</java-type>
        <root-type-qname xmlns:typeNS="http://www.gssamerica.com/mdm/services">typeNS:sortDefinitionType</root-type-qname>
        <qname-scope>complexType</qname-scope>
        <variable-mapping>
            <java-variable-name>sortField</java-variable-name>
            <xml-element-name>sortField</xml-element-name>
        </variable-mapping>
    </java-xml-type-mapping>
    <java-xml-type-mapping>
        <java-type>com.gssamerica.mdm.services.RecordIdentifierType</java-type>
        <root-type-qname xmlns:typeNS="http://www.gssamerica.com/mdm/services">typeNS:recordIdentifierType</root-type-qname>
        <qname-scope>complexType</qname-scope>
        <variable-mapping>
            <java-variable-name>recordId</java-variable-name>
            <xml-element-name>recordId</xml-element-name>
        </variable-mapping>
        <variable-mapping>
            <java-variable-name>externalId</java-variable-name>
            <xml-element-name>externalId</xml-element-name>
        </variable-mapping>
        <variable-mapping>
            <java-variable-name>autoId</java-variable-name>
            <xml-element-name>autoId</xml-element-name>
        </variable-mapping>
        <variable-mapping>
            <java-variable-name>remoteKey</java-variable-name>
            <xml-element-name>remoteKey</xml-element-name>
        </variable-mapping>
        <variable-mapping>
            <java-variable-name>unifiedFields</java-variable-name>
            <xml-element-name>unifiedFields</xml-element-name>
        </variable-mapping>
        <variable-mapping>
            <java-variable-name>table</java-variable-name>
            <xml-element-name>table</xml-element-name>
        </variable-mapping>
    </java-xml-type-mapping>
    <java-xml-type-mapping>
        <java-type>com.gssamerica.mdm.services.ConfigurationDataType</java-type>
        <root-type-qname xmlns:typeNS="http://www.gssamerica.com/mdm/services">typeNS:configurationDataType</root-type-qname>
        <qname-scope>complexType</qname-scope>
        <variable-mapping>
            <java-variable-name>element</java-variable-name>
            <xml-element-name>element</xml-element-name>
        </variable-mapping>
    </java-xml-type-mapping>
    <java-xml-type-mapping>
        <java-type>com.gssamerica.mdm.services.ServiceReturnType</java-type>
        <root-type-qname xmlns:typeNS="http://www.gssamerica.com/mdm/services">typeNS:serviceReturnType</root-type-qname>
        <qname-scope>complexType</qname-scope>
        <variable-mapping>
            <java-variable-name>executionStatus</java-variable-name>
            <xml-element-name>executionStatus</xml-element-name>
        </variable-mapping>
    </java-xml-type-mapping>
    <java-xml-type-mapping>
        <java-type>com.gssamerica.mdm.services.RecordType</java-type>
        <root-type-qname xmlns:typeNS="http://www.gssamerica.com/mdm/services">typeNS:recordType</root-type-qname>
        <qname-scope>complexType</qname-scope>
        <variable-mapping>
            <java-variable-name>dataElement</java-variable-name>
            <xml-element-name>dataElement</xml-element-name>
        </variable-mapping>
        <variable-mapping>
            <java-variable-name>recordIdentifier</java-variable-name>
            <xml-element-name>recordIdentifier</xml-element-name>
        </variable-mapping>
    </java-xml-type-mapping>
    <java-xml-type-mapping>
        <java-type>com.gssamerica.mdm.services.KeyType</java-type>
        <root-type-qname xmlns:typeNS="http://www.gssamerica.com/mdm/services">typeNS:keyType</root-type-qname>
        <qname-scope>complexType</qname-scope>
        <variable-mapping>
            <java-variable-name>isDefault</java-variable-name>
            <xml-element-name>isDefault</xml-element-name>
        </variable-mapping>
        <variable-mapping>
            <java-variable-name>value</java-variable-name>
            <xml-element-name>value</xml-element-name>
        </variable-mapping>
    </java-xml-type-mapping>
    <java-xml-type-mapping>
        <java-type>com.gssamerica.mdm.services.TableType</java-type>
        <root-type-qname xmlns:typeNS="http://www.gssamerica.com/mdm/services">typeNS:tableType</root-type-qname>
        <qname-scope>complexType</qname-scope>
        <variable-mapping>
            <java-variable-name>code</java-variable-name>
            <xml-element-name>code</xml-element-name>
        </variable-mapping>
        <variable-mapping>
            <java-variable-name>tableName</java-variable-name>
            <xml-element-name>tableName</xml-element-name>
        </variable-mapping>
    </java-xml-type-mapping>
    <java-xml-type-mapping>
        <java-type>com.gssamerica.mdm.services.UpdateRecordRequestType</java-type>
        <root-type-qname xmlns:typeNS="http://www.gssamerica.com/mdm/services">typeNS:updateRecordRequestType</root-type-qname>
        <qname-scope>complexType</qname-scope>
        <variable-mapping>
            <java-variable-name>record</java-variable-name>
            <xml-element-name>record</xml-element-name>
        </variable-mapping>
        <variable-mapping>
            <java-variable-name>repositoryInfo</java-variable-name>
            <xml-element-name>repositoryInfo</xml-element-name>
        </variable-mapping>
        <variable-mapping>
            <java-variable-name>configData</java-variable-name>
            <xml-element-name>configData</xml-element-name>
        </variable-mapping>
    </java-xml-type-mapping>
    <java-xml-type-mapping>
        <java-type>com.gssamerica.mdm.services.UnifiedFieldType</java-type>
        <root-type-qname xmlns:typeNS="http://www.gssamerica.com/mdm/services">typeNS:unifiedFieldType</root-type-qname>
        <qname-scope>complexType</qname-scope>
        <variable-mapping>
            <java-variable-name>code</java-variable-name>
            <xml-element-name>code</xml-element-name>
        </variable-mapping>
        <variable-mapping>
            <java-variable-name>fieldName</java-variable-name>
            <xml-element-name>fieldName</xml-element-name>
        </variable-mapping>
    </java-xml-type-mapping>
    <java-xml-type-mapping>
        <java-type>com.gssamerica.mdm.services.PublishUpdatesRequestType</java-type>
        <root-type-qname xmlns:typeNS="http://www.gssamerica.com/mdm/services">typeNS:publishUpdatesRequestType</root-type-qname>
        <qname-scope>complexType</qname-scope>
        <variable-mapping>
            <java-variable-name>record</java-variable-name>
            <xml-element-name>record</xml-element-name>
        </variable-mapping>
        <variable-mapping>
            <java-variable-name>repositoryInfo</java-variable-name>
            <xml-element-name>repositoryInfo</xml-element-name>
        </variable-mapping>
        <variable-mapping>
            <java-variable-name>configData</java-variable-name>
            <xml-element-name>configData</xml-element-name>
        </variable-mapping>
    </java-xml-type-mapping>
    <java-xml-type-mapping>
        <java-type>com.gssamerica.mdm.services.SimpleValueCriteriaType</java-type>
        <root-type-qname xmlns:typeNS="http://www.gssamerica.com/mdm/services">typeNS:simpleValueCriteriaType</root-type-qname>
        <qname-scope>complexType</qname-scope>
        <variable-mapping>
            <java-variable-name>expressionOperator</java-variable-name>
            <xml-element-name>expressionOperator</xml-element-name>
        </variable-mapping>
        <variable-mapping>
            <java-variable-name>unit</java-variable-name>
            <xml-element-name>unit</xml-element-name>
        </variable-mapping>
        <variable-mapping>
            <java-variable-name>value</java-variable-name>
            <xml-element-name>value</xml-element-name>
        </variable-mapping>
    </java-xml-type-mapping>
    <java-xml-type-mapping>
        <java-type>com.gssamerica.mdm.services.RetreiveRemoteKeysType</java-type>
        <root-type-qname xmlns:typeNS="http://www.gssamerica.com/mdm/services">typeNS:retreiveRemoteKeysType</root-type-qname>
        <qname-scope>complexType</qname-scope>
        <variable-mapping>
            <java-variable-name>retreiveRemoteKeys</java-variable-name>
            <xml-element-name>retreiveRemoteKeys</xml-element-name>
        </variable-mapping>
        <variable-mapping>
            <java-variable-name>remoteSystemFilter</java-variable-name>
            <xml-element-name>remoteSystemFilter</xml-element-name>
        </variable-mapping>
    </java-xml-type-mapping>
    <java-xml-type-mapping>
        <java-type>com.gssamerica.mdm.services.ConfigurationDataElementType</java-type>
        <root-type-qname xmlns:typeNS="http://www.gssamerica.com/mdm/services">typeNS:configurationDataElementType</root-type-qname>
        <qname-scope>complexType</qname-scope>
        <variable-mapping>
            <java-variable-name>name</java-variable-name>
            <xml-element-name>name</xml-element-name>
        </variable-mapping>
        <variable-mapping>
            <java-variable-name>value</java-variable-name>
            <xml-element-name>value</xml-element-name>
        </variable-mapping>
    </java-xml-type-mapping>
    <java-xml-type-mapping>
        <java-type>com.gssamerica.mdm.services.RemoteKeyType</java-type>
        <root-type-qname xmlns:typeNS="http://www.gssamerica.com/mdm/services">typeNS:remoteKeyType</root-type-qname>
        <qname-scope>complexType</qname-scope>
        <variable-mapping>
            <java-variable-name>key</java-variable-name>
            <xml-element-name>key</xml-element-name>
        </variable-mapping>
        <variable-mapping>
            <java-variable-name>remoteSystem</java-variable-name>
            <xml-element-name>remoteSystem</xml-element-name>
        </variable-mapping>
    </java-xml-type-mapping>
    <java-xml-type-mapping>
        <java-type>com.gssamerica.mdm.services.FieldType</java-type>
        <root-type-qname xmlns:typeNS="http://www.gssamerica.com/mdm/services">typeNS:fieldType</root-type-qname>
        <qname-scope>complexType</qname-scope>
        <variable-mapping>
            <java-variable-name>dataType</java-variable-name>
            <xml-element-name>dataType</xml-element-name>
        </variable-mapping>
        <variable-mapping>
            <java-variable-name>taxonomyField</java-variable-name>
            <xml-element-name>taxonomyField</xml-element-name>
        </variable-mapping>
        <variable-mapping>
            <java-variable-name>unifiedField</java-variable-name>
            <xml-element-name>unifiedField</xml-element-name>
        </variable-mapping>
    </java-xml-type-mapping>
    <java-xml-type-mapping>
        <java-type>com.gssamerica.mdm.services.LookupValueType</java-type>
        <root-type-qname xmlns:typeNS="http://www.gssamerica.com/mdm/services">typeNS:lookupValueType</root-type-qname>
        <qname-scope>complexType</qname-scope>
        <variable-mapping>
            <java-variable-name>linkId</java-variable-name>
            <xml-element-name>linkId</xml-element-name>
        </variable-mapping>
        <variable-mapping>
            <java-variable-name>record</java-variable-name>
            <xml-element-name>record</xml-element-name>
        </variable-mapping>
    </java-xml-type-mapping>
    <java-xml-type-mapping>
        <java-type>com.gssamerica.mdm.services.ExecutionStatusType</java-type>
        <root-type-qname xmlns:typeNS="http://www.gssamerica.com/mdm/services">typeNS:executionStatusType</root-type-qname>
        <qname-scope>complexType</qname-scope>
        <variable-mapping>
            <java-variable-name>status</java-variable-name>
            <xml-element-name>status</xml-element-name>
        </variable-mapping>
        <variable-mapping>
            <java-variable-name>description</java-variable-name>
            <xml-element-name>description</xml-element-name>
        </variable-mapping>
        <variable-mapping>
            <java-variable-name>dataObject</java-variable-name>
            <xml-element-name>dataObject</xml-element-name>
        </variable-mapping>
        <variable-mapping>
            <java-variable-name>returnValue</java-variable-name>
            <xml-element-name>returnValue</xml-element-name>
        </variable-mapping>
        <variable-mapping>
            <java-variable-name>dataObjectId</java-variable-name>
            <xml-element-name>dataObjectId</xml-element-name>
        </variable-mapping>
        <variable-mapping>
            <java-variable-name>fault</java-variable-name>
            <xml-element-name>fault</xml-element-name>
        </variable-mapping>
    </java-xml-type-mapping>
    <java-xml-type-mapping>
        <java-type>com.gssamerica.mdm.services.CreateRecordRequestType</java-type>
        <root-type-qname xmlns:typeNS="http://www.gssamerica.com/mdm/services">typeNS:createRecordRequestType</root-type-qname>
        <qname-scope>complexType</qname-scope>
        <variable-mapping>
            <java-variable-name>record</java-variable-name>
            <xml-element-name>record</xml-element-name>
        </variable-mapping>
        <variable-mapping>
            <java-variable-name>repositoryInfo</java-variable-name>
            <xml-element-name>repositoryInfo</xml-element-name>
        </variable-mapping>
        <variable-mapping>
            <java-variable-name>configData</java-variable-name>
            <xml-element-name>configData</xml-element-name>
        </variable-mapping>
    </java-xml-type-mapping>
    <java-xml-type-mapping>
        <java-type>com.gssamerica.mdm.services.SearchRecordRequestType</java-type>
        <root-type-qname xmlns:typeNS="http://www.gssamerica.com/mdm/services">typeNS:searchRecordRequestType</root-type-qname>
        <qname-scope>complexType</qname-scope>
        <variable-mapping>
            <java-variable-name>query</java-variable-name>
            <xml-element-name>query</xml-element-name>
        </variable-mapping>
        <variable-mapping>
            <java-variable-name>repositoryInfo</java-variable-name>
            <xml-element-name>repositoryInfo</xml-element-name>
        </variable-mapping>
        <variable-mapping>
            <java-variable-name>configData</java-variable-name>
            <xml-element-name>configData</xml-element-name>
        </variable-mapping>
    </java-xml-type-mapping>
    <java-xml-type-mapping>
        <java-type>com.gssamerica.mdm.services.UnifiedValueType</java-type>
        <root-type-qname xmlns:typeNS="http://www.gssamerica.com/mdm/services">typeNS:unifiedValueType</root-type-qname>
        <qname-scope>complexType</qname-scope>
        <variable-mapping>
            <java-variable-name>unit</java-variable-name>
            <xml-element-name>unit</xml-element-name>
        </variable-mapping>
        <variable-mapping>
            <java-variable-name>value</java-variable-name>
            <xml-element-name>value</xml-element-name>
        </variable-mapping>
    </java-xml-type-mapping>
    <java-xml-type-mapping>
        <java-type>com.gssamerica.mdm.services.DataElementCriteriaType</java-type>
        <root-type-qname xmlns:typeNS="http://www.gssamerica.com/mdm/services">typeNS:dataElementCriteriaType</root-type-qname>
        <qname-scope>complexType</qname-scope>
        <variable-mapping>
            <java-variable-name>fieldCode</java-variable-name>
            <xml-element-name>fieldCode</xml-element-name>
        </variable-mapping>
        <variable-mapping>
            <java-variable-name>taxonomyFieldCode</java-variable-name>
            <xml-element-name>taxonomyFieldCode</xml-element-name>
        </variable-mapping>
        <variable-mapping>
            <java-variable-name>dataType</java-variable-name>
            <xml-element-name>dataType</xml-element-name>
        </variable-mapping>
        <variable-mapping>
            <java-variable-name>logicOperator</java-variable-name>
            <xml-element-name>logicOperator</xml-element-name>
        </variable-mapping>
        <variable-mapping>
            <java-variable-name>simpleValueCriteria</java-variable-name>
            <xml-element-name>simpleValueCriteria</xml-element-name>
        </variable-mapping>
        <variable-mapping>
            <java-variable-name>lookupValueCriteria</java-variable-name>
            <xml-element-name>lookupValueCriteria</xml-element-name>
        </variable-mapping>
    </java-xml-type-mapping>
    <java-xml-type-mapping>
        <java-type>com.gssamerica.mdm.services.KeyMappingQuereyRequestType</java-type>
        <root-type-qname xmlns:typeNS="http://www.gssamerica.com/mdm/services">typeNS:keyMappingQuereyRequestType</root-type-qname>
        <qname-scope>complexType</qname-scope>
        <variable-mapping>
            <java-variable-name>recordIdentifierRequest</java-variable-name>
            <xml-element-name>recordIdentifierRequest</xml-element-name>
        </variable-mapping>
    </java-xml-type-mapping>
    <java-xml-type-mapping>
        <java-type>com.gssamerica.mdm.services.RecordIdentifierCriteriaType</java-type>
        <root-type-qname xmlns:typeNS="http://www.gssamerica.com/mdm/services">typeNS:recordIdentifierCriteriaType</root-type-qname>
        <qname-scope>complexType</qname-scope>
        <variable-mapping>
            <java-variable-name>autoId</java-variable-name>
            <xml-element-name>autoId</xml-element-name>
        </variable-mapping>
        <variable-mapping>
            <java-variable-name>externalId</java-variable-name>
            <xml-element-name>externalId</xml-element-name>
        </variable-mapping>
        <variable-mapping>
            <java-variable-name>recordId</java-variable-name>
            <xml-element-name>recordId</xml-element-name>
        </variable-mapping>
        <variable-mapping>
            <java-variable-name>remoteKey</java-variable-name>
            <xml-element-name>remoteKey</xml-element-name>
        </variable-mapping>
    </java-xml-type-mapping>
    <java-xml-type-mapping>
        <java-type>com.gssamerica.mdm.services.RepositoryInformationType</java-type>
        <root-type-qname xmlns:typeNS="http://www.gssamerica.com/mdm/services">typeNS:repositoryInformationType</root-type-qname>
        <qname-scope>complexType</qname-scope>
        <variable-mapping>
            <java-variable-name>dataLang</java-variable-name>
            <xml-element-name>dataLang</xml-element-name>
        </variable-mapping>
        <variable-mapping>
            <java-variable-name>repositoryName</java-variable-name>
            <xml-element-name>repositoryName</xml-element-name>
        </variable-mapping>
        <variable-mapping>
            <java-variable-name>repositoryPort</java-variable-name>
            <xml-element-name>repositoryPort</xml-element-name>
        </variable-mapping>
        <variable-mapping>
            <java-variable-name>serverName</java-variable-name>
            <xml-element-name>serverName</xml-element-name>
        </variable-mapping>
        <variable-mapping>
            <java-variable-name>schemaLang</java-variable-name>
            <xml-element-name>schemaLang</xml-element-name>
        </variable-mapping>
    </java-xml-type-mapping>
    <java-xml-type-mapping>
        <java-type>com.gssamerica.mdm.services.QueryType</java-type>
        <root-type-qname xmlns:typeNS="http://www.gssamerica.com/mdm/services">typeNS:queryType</root-type-qname>
        <qname-scope>complexType</qname-scope>
        <variable-mapping>
            <java-variable-name>recordCriteria</java-variable-name>
            <xml-element-name>recordCriteria</xml-element-name>
        </variable-mapping>
        <variable-mapping>
            <java-variable-name>resultDefinition</java-variable-name>
            <xml-element-name>resultDefinition</xml-element-name>
        </variable-mapping>
    </java-xml-type-mapping>
    <java-xml-type-mapping>
        <java-type>com.gssamerica.mdm.services.FieldDefinitionType</java-type>
        <root-type-qname xmlns:typeNS="http://www.gssamerica.com/mdm/services">typeNS:fieldDefinitionType</root-type-qname>
        <qname-scope>complexType</qname-scope>
        <variable-mapping>
            <java-variable-name>loadAttributes</java-variable-name>
            <xml-element-name>loadAttributes</xml-element-name>
        </variable-mapping>
        <variable-mapping>
            <java-variable-name>lookupLevel</java-variable-name>
            <xml-element-name>lookupLevel</xml-element-name>
        </variable-mapping>
        <variable-mapping>
            <java-variable-name>fieldCode</java-variable-name>
            <xml-element-name>fieldCode</xml-element-name>
        </variable-mapping>
    </java-xml-type-mapping>
    <java-xml-type-mapping>
        <java-type>com.gssamerica.mdm.services.ValueType</java-type>
        <root-type-qname xmlns:typeNS="http://www.gssamerica.com/mdm/services">typeNS:valueType</root-type-qname>
        <qname-scope>complexType</qname-scope>
        <variable-mapping>
            <java-variable-name>language</java-variable-name>
            <xml-element-name>language</xml-element-name>
        </variable-mapping>
        <variable-mapping>
            <java-variable-name>value</java-variable-name>
            <xml-element-name>value</xml-element-name>
        </variable-mapping>
    </java-xml-type-mapping>
    <java-xml-type-mapping>
        <java-type>com.gssamerica.mdm.services.LookupValueCriteria</java-type>
        <anonymous-type-qname>{http://www.gssamerica.com/mdm/services}&gt;dataElementCriteriaType&gt;lookupValueCriteria</anonymous-type-qname>
        <qname-scope>complexType</qname-scope>
        <variable-mapping>
            <java-variable-name>tableCode</java-variable-name>
            <xml-element-name>tableCode</xml-element-name>
        </variable-mapping>
        <variable-mapping>
            <java-variable-name>dataElementCriteria</java-variable-name>
            <xml-element-name>dataElementCriteria</xml-element-name>
        </variable-mapping>
    </java-xml-type-mapping>
    <java-xml-type-mapping>
        <java-type>com.gssamerica.mdm.services.FaultType</java-type>
        <root-type-qname xmlns:typeNS="http://www.gssamerica.com/mdm/services">typeNS:faultType</root-type-qname>
        <qname-scope>complexType</qname-scope>
        <variable-mapping>
            <java-variable-name>severity</java-variable-name>
            <xml-element-name>severity</xml-element-name>
        </variable-mapping>
        <variable-mapping>
            <java-variable-name>faultId</java-variable-name>
            <xml-element-name>faultId</xml-element-name>
        </variable-mapping>
        <variable-mapping>
            <java-variable-name>faultText</java-variable-name>
            <xml-element-name>faultText</xml-element-name>
        </variable-mapping>
    </java-xml-type-mapping>
    <java-xml-type-mapping>
        <java-type>com.gssamerica.mdm.services.SortFieldType</java-type>
        <root-type-qname xmlns:typeNS="http://www.gssamerica.com/mdm/services">typeNS:sortFieldType</root-type-qname>
        <qname-scope>complexType</qname-scope>
        <variable-mapping>
            <java-variable-name>isAscending</java-variable-name>
            <xml-element-name>isAscending</xml-element-name>
        </variable-mapping>
        <variable-mapping>
            <java-variable-name>fieldCode</java-variable-name>
            <xml-element-name>fieldCode</xml-element-name>
        </variable-mapping>
    </java-xml-type-mapping>
    <java-xml-type-mapping>
        <java-type>com.gssamerica.mdm.services.RecordIdentifierType[]</java-type>
        <anonymous-type-qname>{http://www.gssamerica.com/mdm/services}addRemoteKeyRequestType&gt;recordIdentifier[1,unbounded]</anonymous-type-qname>
        <qname-scope>complexType</qname-scope>
    </java-xml-type-mapping>
    <java-xml-type-mapping>
        <java-type>com.gssamerica.mdm.services.RemoteKeyType[]</java-type>
        <anonymous-type-qname>{http://www.gssamerica.com/mdm/services}recordIdentifierType&gt;remoteKey[0,unbounded]</anonymous-type-qname>
        <qname-scope>complexType</qname-scope>
    </java-xml-type-mapping>
    <java-xml-type-mapping>
        <java-type>com.gssamerica.mdm.services.DataElementType[]</java-type>
        <anonymous-type-qname>{http://www.gssamerica.com/mdm/services}recordIdentifierType&gt;unifiedFields[0,unbounded]</anonymous-type-qname>
        <qname-scope>complexType</qname-scope>
    </java-xml-type-mapping>
    <java-xml-type-mapping>
        <java-type>com.gssamerica.mdm.services.DataElementType[]</java-type>
        <anonymous-type-qname>{http://www.gssamerica.com/mdm/services}recordType&gt;dataElement[1,unbounded]</anonymous-type-qname>
        <qname-scope>complexType</qname-scope>
    </java-xml-type-mapping>
    <java-xml-type-mapping>
        <java-type>com.gssamerica.mdm.services.ConfigurationDataElementType[]</java-type>
        <anonymous-type-qname>{http://www.gssamerica.com/mdm/services}configurationDataType&gt;element[0,unbounded]</anonymous-type-qname>
        <qname-scope>complexType</qname-scope>
    </java-xml-type-mapping>
    <java-xml-type-mapping>
        <java-type>com.gssamerica.mdm.services.ExecutionStatusType[]</java-type>
        <anonymous-type-qname>{http://www.gssamerica.com/mdm/services}serviceReturnType&gt;executionStatus[0,unbounded]</anonymous-type-qname>
        <qname-scope>complexType</qname-scope>
    </java-xml-type-mapping>
    <java-xml-type-mapping>
        <java-type>java.lang.String[]</java-type>
        <anonymous-type-qname>{http://www.gssamerica.com/mdm/services}retreiveRemoteKeysType&gt;remoteSystemFilter[0,unbounded]</anonymous-type-qname>
        <qname-scope>complexType</qname-scope>
    </java-xml-type-mapping>
    <java-xml-type-mapping>
        <java-type>com.gssamerica.mdm.services.RecordIdentifierType[]</java-type>
        <anonymous-type-qname>{http://www.gssamerica.com/mdm/services}delRemoteKeyRequestType&gt;recordIdentifier[1,unbounded]</anonymous-type-qname>
        <qname-scope>complexType</qname-scope>
    </java-xml-type-mapping>
    <java-xml-type-mapping>
        <java-type>java.lang.String[]</java-type>
        <anonymous-type-qname>{http://www.gssamerica.com/mdm/services}remoteSystemFilterType&gt;remoteSystem[0,unbounded]</anonymous-type-qname>
        <qname-scope>complexType</qname-scope>
    </java-xml-type-mapping>
    <java-xml-type-mapping>
        <java-type>com.gssamerica.mdm.services.DataElementCriteriaType[]</java-type>
        <anonymous-type-qname>{http://www.gssamerica.com/mdm/services}recordCriteriaType&gt;dataElementCriteria[0,unbounded]</anonymous-type-qname>
        <qname-scope>complexType</qname-scope>
    </java-xml-type-mapping>
    <java-xml-type-mapping>
        <java-type>com.gssamerica.mdm.services.DataElementCriteriaType[]</java-type>
        <anonymous-type-qname>{http://www.gssamerica.com/mdm/services}&gt;dataElementCriteriaType&gt;lookupValueCriteria&gt;dataElementCriteria[1,unbounded]</anonymous-type-qname>
        <qname-scope>complexType</qname-scope>
    </java-xml-type-mapping>
    <java-xml-type-mapping>
        <java-type>com.gssamerica.mdm.services.RecordIdentifierCriteriaType[]</java-type>
        <anonymous-type-qname>{http://www.gssamerica.com/mdm/services}recordCriteriaType&gt;recordIdentifierCriteria[0,unbounded]</anonymous-type-qname>
        <qname-scope>complexType</qname-scope>
    </java-xml-type-mapping>
    <java-xml-type-mapping>
        <java-type>com.gssamerica.mdm.services.SimpleValueCriteriaType[]</java-type>
        <anonymous-type-qname>{http://www.gssamerica.com/mdm/services}recordCriteriaType&gt;keywordCriteria[0,unbounded]</anonymous-type-qname>
        <qname-scope>complexType</qname-scope>
    </java-xml-type-mapping>
    <java-xml-type-mapping>
        <java-type>com.gssamerica.mdm.services.RecordType[]</java-type>
        <anonymous-type-qname>{http://www.gssamerica.com/mdm/services}updateRecordRequestType&gt;record[1,unbounded]</anonymous-type-qname>
        <qname-scope>complexType</qname-scope>
    </java-xml-type-mapping>
    <java-xml-type-mapping>
        <java-type>com.gssamerica.mdm.services.RecordType[]</java-type>
        <anonymous-type-qname>{http://www.gssamerica.com/mdm/services}publishUpdatesRequestType&gt;record[1,unbounded]</anonymous-type-qname>
        <qname-scope>complexType</qname-scope>
    </java-xml-type-mapping>
    <java-xml-type-mapping>
        <java-type>com.gssamerica.mdm.services.RecordType[]</java-type>
        <anonymous-type-qname>{http://www.gssamerica.com/mdm/services}createRecordRequestType&gt;record[1,unbounded]</anonymous-type-qname>
        <qname-scope>complexType</qname-scope>
    </java-xml-type-mapping>
    <java-xml-type-mapping>
        <java-type>com.gssamerica.mdm.services.RecordIdentifierRequestType[]</java-type>
        <anonymous-type-qname>{http://www.gssamerica.com/mdm/services}keyMappingQuereyRequestType&gt;recordIdentifierRequest[1,unbounded]</anonymous-type-qname>
        <qname-scope>complexType</qname-scope>
    </java-xml-type-mapping>
    <service-interface-mapping>
        <service-interface>com.gssamerica.mdm.services.addremotekey.AddRemoteKeyService</service-interface>
        <wsdl-service-name xmlns:serviceNS="http://www.gssamerica.com/mdm/services/AddRemoteKeyService/">serviceNS:AddRemoteKeyService</wsdl-service-name>
        <port-mapping>
            <port-name>AddRemoteKeySOAP</port-name>
            <java-port-name>AddRemoteKeySOAP</java-port-name>
        </port-mapping>
    </service-interface-mapping>
    <service-endpoint-interface-mapping>
        <service-endpoint-interface>com.gssamerica.mdm.services.addremotekey.AddRemoteKey</service-endpoint-interface>
        <wsdl-port-type xmlns:portTypeNS="http://www.gssamerica.com/mdm/services/AddRemoteKeyService/">portTypeNS:AddRemoteKey</wsdl-port-type>
        <wsdl-binding xmlns:bindingNS="http://www.gssamerica.com/mdm/services/AddRemoteKeyService/">bindingNS:AddRemoteKeySOAP</wsdl-binding>
        <service-endpoint-method-mapping>
            <java-method-name>addRemoteKey</java-method-name>
            <wsdl-operation>addRemoteKey</wsdl-operation>
            <method-param-parts-mapping>
                <param-position>0</param-position>
                <param-type>com.gssamerica.mdm.services.AddRemoteKeyRequestType</param-type>
                <wsdl-message-mapping>
                    <wsdl-message xmlns:wsdlMsgNS="http://www.gssamerica.com/mdm/services/AddRemoteKeyService/">wsdlMsgNS:AddRemoteKeyRequest</wsdl-message>
                    <wsdl-message-part-name>AddRemoteKeyRequest</wsdl-message-part-name>
                    <parameter-mode>IN</parameter-mode>
                </wsdl-message-mapping>
            </method-param-parts-mapping>
            <wsdl-return-value-mapping>
                <method-return-value>com.gssamerica.mdm.services.ServiceReturnType</method-return-value>
                <wsdl-message xmlns:wsdlMsgNS="http://www.gssamerica.com/mdm/services/AddRemoteKeyService/">wsdlMsgNS:AddRemoteKeyResponse</wsdl-message>
                <wsdl-message-part-name>AddRemoteKeyResponse</wsdl-message-part-name>
            </wsdl-return-value-mapping>
        </service-endpoint-method-mapping>
    </service-endpoint-interface-mapping>
</java-wsdl-mapping>

